{
    "chain_name": "tellor",
    "api": [
      {"provider": "tellorlayer.com", "address": "http://tellorlayer.com:1317"}
    ],
    "rpc": [
      {"provider": "tellorlayer.com", "address": "http://tellorlayer.com:26657"}
    ],
    "sdk_version": "0.45.15",
    "coin_type": "118",
    "min_tx_fee": "5000",
    "addr_prefix": "allo",
    "logo": "/logos/tellor.png",
    "keplr_features": ["ibc-transfer", "ibc-go"],
    "theme_color": "#14a278",
    "assets": [
      {
        "base": "loya",
        "symbol": "LOYA",
        "exponent": "6",
        "coingecko_id": "",
        "logo": "/logos/tellor.png"
      }
    ]
  }